fuzzyroutines/Examples.py
fuzzyroutines/FuzzyRoutines.py
fuzzyroutines/__init__.py
fuzzyroutines-1.0.3.dist-info/LICENSE
fuzzyroutines-1.0.3.dist-info/METADATA
fuzzyroutines-1.0.3.dist-info/WHEEL
fuzzyroutines-1.0.3.dist-info/top_level.txt
fuzzyroutines-1.0.3.dist-info/zip-safe
fuzzyroutines-1.0.3.dist-info/RECORD
